setup.py
DeepFramework.egg-info/PKG-INFO
DeepFramework.egg-info/SOURCES.txt
DeepFramework.egg-info/dependency_links.txt
DeepFramework.egg-info/not-zip-safe
DeepFramework.egg-info/requires.txt
DeepFramework.egg-info/top_level.txt
dframe/__init__.py
dframe/dataset/__init__.py
dframe/dataset/dataset.py
dframe/dataset/persistence.py
dframe/dataset/sample.py
dframe/model/__init__.py
dframe/model/model.py
dframe/pipeline/__init__.py
dframe/pipeline/core.py
dframe/pipeline/package.py
dframe/pipeline/pipeline.py