Metadata-Version: 1.0
Name: DeepFramework
Version: 0.1.6
Summary: Python framework for Deep Learning
Home-page: https://github.com/issey173/deepframework.git
Author: Issey Masuda Mora
Author-email: issey173@gmail.com
License: MIT
Platform: UNKNOWN
